happymailer/__init__.py
happymailer/admin.py
happymailer/apps.py
happymailer/fake.py
happymailer/forms.py
happymailer/models.py
happymailer/receivers.py
happymailer/utils.py
happymailer/views.py
happymailer/backends/__init__.py
happymailer/backends/base.py
happymailer/backends/mjml.py
happymailer/management/__init__.py
happymailer/management/commands/__init__.py
happymailer/management/commands/create_email_templates.py
happymailer/migrations/0001_initial.py
happymailer/migrations/0002_extend_template_history.py
happymailer/migrations/__init__.py
happymailer/templates/admin/happymailer/templatemodel/base.html
happymailer/templates/admin/happymailer/templatemodel/change_form.html
happymailer/templates/admin/happymailer/templatemodel/change_list.html
happymailer/templates/admin/happymailer/templatemodel/import.html
happymailer/templates/admin/happymailer/templatemodel/preview.html
happymailer/tests/__init__.py
happymailer/tests/test_fake.py
happymailer/tests/test_mjml.py
happymailer/tests/test_template.py
django_happymailer-0.3.1.dist-info/METADATA
django_happymailer-0.3.1.dist-info/WHEEL
django_happymailer-0.3.1.dist-info/top_level.txt
django_happymailer-0.3.1.dist-info/RECORD
