Metadata-Version: 2.1
Name: django-happymailer
Version: 0.3.1
Summary: django email templates manager
Home-page: UNKNOWN
Author: Victor Kotcheruba
Author-email: barbuzaster@gmail.com
Maintainer: Dmitrii Gerasimenko
Maintainer-email: kiddima@gmail.com
License: UNKNOWN
Platform: UNKNOWN
Requires-Dist: django (>=3.0)
Requires-Dist: django-import-export (>=0.4.5)
Requires-Dist: faker (>=0.8.6)
Requires-Dist: html2text (>=2016.5.29)
Requires-Dist: trafaret (<=0.8,>=0.7)
Requires-Dist: six
